{"login":"QubesOS","name":"Qubes OS Project","url":"https://api.github.com/orgs/QubesOS","description":"","created_at":"2014-12-16T20:43:04Z","repos":[{"name":"qubes-core-agent-linux","html_url":"https://github.com/QubesOS/qubes-core-agent-linux","id":30624145,"languages_url":"https://api.github.com/repos/QubesOS/qubes-core-agent-linux/languages","created_at":"2015-02-11T01:27:32Z","languages":[{"name":"Shell","nbrBytes":117060},{"name":"C","nbrBytes":99724},{"name":"Python","nbrBytes":58484},{"name":"Makefile","nbrBytes":20709}]},{"name":"qubes-app-linux-pdf-converter","html_url":"https://github.com/QubesOS/qubes-app-linux-pdf-converter","id":30624131,"languages_url":"https://api.github.com/repos/QubesOS/qubes-app-linux-pdf-converter/languages","created_at":"2015-02-11T01:27:26Z","languages":[{"name":"Shell","nbrBytes":10131},{"name":"Python","nbrBytes":9116},{"name":"Makefile","nbrBytes":4781}]},{"name":"qubes-app-thunderbird","html_url":"https://github.com/QubesOS/qubes-app-thunderbird","id":30624137,"languages_url":"https://api.github.com/repos/QubesOS/qubes-app-thunderbird/languages","created_at":"2015-02-11T01:27:28Z","languages":[{"name":"JavaScript","nbrBytes":6072},{"name":"Makefile","nbrBytes":4999},{"name":"CSS","nbrBytes":530}]},{"name":"qubes-artwork","html_url":"https://github.com/QubesOS/qubes-artwork","id":30624139,"languages_url":"https://api.github.com/repos/QubesOS/qubes-artwork/languages","created_at":"2015-02-11T01:27:29Z","languages":[{"name":"Makefile","nbrBytes":7359},{"name":"Python","nbrBytes":1662},{"name":"Shell","nbrBytes":1642},{"name":"Ruby","nbrBytes":86}]},{"name":"qubes-secpack","html_url":"https://github.com/QubesOS/qubes-secpack","id":28819889,"languages_url":"https://api.github.com/repos/QubesOS/qubes-secpack/languages","created_at":"2015-01-05T16:02:42Z","languages":[{"name":"Python","nbrBytes":1699},{"name":"Shell","nbrBytes":501}]},{"name":"qubes-core-admin","html_url":"https://github.com/QubesOS/qubes-core-admin","id":30624141,"languages_url":"https://api.github.com/repos/QubesOS/qubes-core-admin/languages","created_at":"2015-02-11T01:27:30Z","languages":[{"name":"Python","nbrBytes":1426960},{"name":"Shell","nbrBytes":25934},{"name":"Makefile","nbrBytes":12019},{"name":"C","nbrBytes":2707},{"name":"Ruby","nbrBytes":149}]},{"name":"qubes-app-linux-split-gpg","html_url":"https://github.com/QubesOS/qubes-app-linux-split-gpg","id":30624135,"languages_url":"https://api.github.com/repos/QubesOS/qubes-app-linux-split-gpg/languages","created_at":"2015-02-11T01:27:27Z","languages":[{"name":"C","nbrBytes":38686},{"name":"Python","nbrBytes":33107},{"name":"Makefile","nbrBytes":6302},{"name":"Shell","nbrBytes":4410}]},{"name":"qubes-antievilmaid","html_url":"https://github.com/QubesOS/qubes-antievilmaid","id":30624128,"languages_url":"https://api.github.com/repos/QubesOS/qubes-antievilmaid/languages","created_at":"2015-02-11T01:27:20Z","languages":[{"name":"Shell","nbrBytes":28861},{"name":"C","nbrBytes":1943},{"name":"Ruby","nbrBytes":184}]},{"name":"qubes-app-linux-tor","html_url":"https://github.com/QubesOS/qubes-app-linux-tor","id":30624136,"languages_url":"https://api.github.com/repos/QubesOS/qubes-app-linux-tor/languages","created_at":"2015-02-11T01:27:27Z","languages":[{"name":"Shell","nbrBytes":6495},{"name":"Makefile","nbrBytes":3898},{"name":"Smarty","nbrBytes":791}]},{"name":"qubes-core-admin-linux","html_url":"https://github.com/QubesOS/qubes-core-admin-linux","id":30624143,"languages_url":"https://api.github.com/repos/QubesOS/qubes-core-admin-linux/languages","created_at":"2015-02-11T01:27:31Z","languages":[{"name":"C","nbrBytes":57499},{"name":"Shell","nbrBytes":20182},{"name":"Python","nbrBytes":4996},{"name":"Makefile","nbrBytes":1795},{"name":"Ruby","nbrBytes":116}]},{"name":"qubes-core-vchan-xen","html_url":"https://github.com/QubesOS/qubes-core-vchan-xen","id":30624146,"languages_url":"https://api.github.com/repos/QubesOS/qubes-core-vchan-xen/languages","created_at":"2015-02-11T01:27:33Z","languages":[{"name":"C","nbrBytes":45867},{"name":"Makefile","nbrBytes":4995},{"name":"C++","nbrBytes":2233},{"name":"Shell","nbrBytes":2046},{"name":"PowerShell","nbrBytes":428},{"name":"Batchfile","nbrBytes":46}]},{"name":"qubes-gui-agent-xen-hvm-stubdom","html_url":"https://github.com/QubesOS/qubes-gui-agent-xen-hvm-stubdom","id":30624152,"languages_url":"https://api.github.com/repos/QubesOS/qubes-gui-agent-xen-hvm-stubdom/languages","created_at":"2015-02-11T01:27:36Z","languages":[{"name":"C","nbrBytes":31985},{"name":"Python","nbrBytes":3120}]},{"name":"qubes-gui-agent-linux","html_url":"https://github.com/QubesOS/qubes-gui-agent-linux","id":30624150,"languages_url":"https://api.github.com/repos/QubesOS/qubes-gui-agent-linux/languages","created_at":"2015-02-11T01:27:35Z","languages":[{"name":"C","nbrBytes":5311790},{"name":"C++","nbrBytes":537481},{"name":"Objective-C","nbrBytes":116050},{"name":"Shell","nbrBytes":35123},{"name":"Csound","nbrBytes":23570},{"name":"Makefile","nbrBytes":15418},{"name":"Python","nbrBytes":8900},{"name":"M4","nbrBytes":5665},{"name":"Ruby","nbrBytes":361}]},{"name":"qubes-gui-daemon","html_url":"https://github.com/QubesOS/qubes-gui-daemon","id":30624159,"languages_url":"https://api.github.com/repos/QubesOS/qubes-gui-daemon/languages","created_at":"2015-02-11T01:27:38Z","languages":[{"name":"C","nbrBytes":223870},{"name":"Python","nbrBytes":19298},{"name":"Makefile","nbrBytes":7070},{"name":"C++","nbrBytes":907},{"name":"Shell","nbrBytes":76},{"name":"Ruby","nbrBytes":74}]},{"name":"qubes-desktop-linux-xfce4","html_url":"https://github.com/QubesOS/qubes-desktop-linux-xfce4","id":30624148,"languages_url":"https://api.github.com/repos/QubesOS/qubes-desktop-linux-xfce4/languages","created_at":"2015-02-11T01:27:34Z","languages":[{"name":"Makefile","nbrBytes":517},{"name":"Ruby","nbrBytes":174}]},{"name":"qubes-gui-common","html_url":"https://github.com/QubesOS/qubes-gui-common","id":30624154,"languages_url":"https://api.github.com/repos/QubesOS/qubes-gui-common/languages","created_at":"2015-02-11T01:27:37Z","languages":[{"name":"C","nbrBytes":6521},{"name":"Shell","nbrBytes":894},{"name":"Ruby","nbrBytes":244}]},{"name":"qubes-desktop-linux-kde","html_url":"https://github.com/QubesOS/qubes-desktop-linux-kde","id":30624147,"languages_url":"https://api.github.com/repos/QubesOS/qubes-desktop-linux-kde/languages","created_at":"2015-02-11T01:27:33Z","languages":[{"name":"C++","nbrBytes":75793},{"name":"CMake","nbrBytes":2379},{"name":"Makefile","nbrBytes":2137},{"name":"Python","nbrBytes":1742},{"name":"JavaScript","nbrBytes":1712},{"name":"Ruby","nbrBytes":402},{"name":"Roff","nbrBytes":158}]},{"name":"qubes-installer-qubes-os","html_url":"https://github.com/QubesOS/qubes-installer-qubes-os","id":30624163,"languages_url":"https://api.github.com/repos/QubesOS/qubes-installer-qubes-os/languages","created_at":"2015-02-11T01:27:39Z","languages":[{"name":"HTML","nbrBytes":2630836},{"name":"Python","nbrBytes":2486735},{"name":"Makefile","nbrBytes":1498874},{"name":"Shell","nbrBytes":458096},{"name":"C","nbrBytes":223563},{"name":"M4","nbrBytes":164102},{"name":"JavaScript","nbrBytes":97693},{"name":"CSS","nbrBytes":24610},{"name":"Limbo","nbrBytes":2050},{"name":"OpenEdge ABL","nbrBytes":494},{"name":"TeX","nbrBytes":160}]},{"name":"qubes-linux-kernel","html_url":"https://github.com/QubesOS/qubes-linux-kernel","id":30624165,"languages_url":"https://api.github.com/repos/QubesOS/qubes-linux-kernel/languages","created_at":"2015-02-11T01:27:39Z","languages":[{"name":"Perl","nbrBytes":7632},{"name":"Makefile","nbrBytes":3404},{"name":"Shell","nbrBytes":1528},{"name":"Ruby","nbrBytes":214}]},{"name":"qubes-linux-template-builder","html_url":"https://github.com/QubesOS/qubes-linux-template-builder","id":30624172,"languages_url":"https://api.github.com/repos/QubesOS/qubes-linux-template-builder/languages","created_at":"2015-02-11T01:27:42Z","languages":[{"name":"Shell","nbrBytes":63296},{"name":"Makefile","nbrBytes":2588}]},{"name":"qubes-vmm-xen","html_url":"https://github.com/QubesOS/qubes-vmm-xen","id":30624178,"languages_url":"https://api.github.com/repos/QubesOS/qubes-vmm-xen/languages","created_at":"2015-02-11T01:27:45Z","languages":[{"name":"C","nbrBytes":19537},{"name":"Makefile","nbrBytes":7498},{"name":"Shell","nbrBytes":5184},{"name":"Ruby","nbrBytes":863}]},{"name":"qubes-linux-utils","html_url":"https://github.com/QubesOS/qubes-linux-utils","id":30624173,"languages_url":"https://api.github.com/repos/QubesOS/qubes-linux-utils/languages","created_at":"2015-02-11T01:27:43Z","languages":[{"name":"C","nbrBytes":58916},{"name":"Shell","nbrBytes":19695},{"name":"Python","nbrBytes":14773},{"name":"Makefile","nbrBytes":5955},{"name":"Ruby","nbrBytes":139}]},{"name":"qubes-vmm-xen-windows-pvdrivers","html_url":"https://github.com/QubesOS/qubes-vmm-xen-windows-pvdrivers","id":30624179,"languages_url":"https://api.github.com/repos/QubesOS/qubes-vmm-xen-windows-pvdrivers/languages","created_at":"2015-02-11T01:27:46Z","languages":[{"name":"C","nbrBytes":47498},{"name":"Python","nbrBytes":8815},{"name":"Batchfile","nbrBytes":1311},{"name":"PowerShell","nbrBytes":423},{"name":"Ruby","nbrBytes":242},{"name":"Makefile","nbrBytes":55}]},{"name":"qubes-core-agent-windows","html_url":"https://github.com/QubesOS/qubes-core-agent-windows","id":31260813,"languages_url":"https://api.github.com/repos/QubesOS/qubes-core-agent-windows/languages","created_at":"2015-02-24T13:18:01Z","languages":[{"name":"C","nbrBytes":273985},{"name":"C#","nbrBytes":6057},{"name":"Objective-C","nbrBytes":5742},{"name":"PowerShell","nbrBytes":4774},{"name":"Ruby","nbrBytes":232},{"name":"Batchfile","nbrBytes":44}]},{"name":"qubes-builder","html_url":"https://github.com/QubesOS/qubes-builder","id":30625690,"languages_url":"https://api.github.com/repos/QubesOS/qubes-builder/languages","created_at":"2015-02-11T02:12:21Z","languages":[{"name":"Python","nbrBytes":214983},{"name":"Makefile","nbrBytes":79212},{"name":"Shell","nbrBytes":38631}]},{"name":"qubes-linux-yum","html_url":"https://github.com/QubesOS/qubes-linux-yum","id":30624175,"languages_url":"https://api.github.com/repos/QubesOS/qubes-linux-yum/languages","created_at":"2015-02-11T01:27:43Z","languages":[{"name":"Shell","nbrBytes":6784},{"name":"Python","nbrBytes":5170}]},{"name":"qubes-manager","html_url":"https://github.com/QubesOS/qubes-manager","id":30624176,"languages_url":"https://api.github.com/repos/QubesOS/qubes-manager/languages","created_at":"2015-02-11T01:27:44Z","languages":[{"name":"Python","nbrBytes":163869},{"name":"QMake","nbrBytes":1682},{"name":"Makefile","nbrBytes":1490},{"name":"Shell","nbrBytes":765},{"name":"Ruby","nbrBytes":70}]},{"name":"qubes-core-qubesdb","html_url":"https://github.com/QubesOS/qubes-core-qubesdb","id":30629574,"languages_url":"https://api.github.com/repos/QubesOS/qubes-core-qubesdb/languages","created_at":"2015-02-11T03:55:01Z","languages":[{"name":"C","nbrBytes":113619},{"name":"Makefile","nbrBytes":4185},{"name":"Shell","nbrBytes":2382},{"name":"Python","nbrBytes":640},{"name":"PowerShell","nbrBytes":428},{"name":"Batchfile","nbrBytes":46}]},{"name":"qubes-core-libvirt","html_url":"https://github.com/QubesOS/qubes-core-libvirt","id":30629566,"languages_url":"https://api.github.com/repos/QubesOS/qubes-core-libvirt/languages","created_at":"2015-02-11T03:54:48Z","languages":[{"name":"Makefile","nbrBytes":2157},{"name":"Shell","nbrBytes":1793},{"name":"Ruby","nbrBytes":655}]},{"name":"qubesos.github.io","html_url":"https://github.com/QubesOS/qubesos.github.io","id":31214926,"languages_url":"https://api.github.com/repos/QubesOS/qubesos.github.io/languages","created_at":"2015-02-23T15:47:19Z","languages":[{"name":"CSS","nbrBytes":85145},{"name":"HTML","nbrBytes":57770},{"name":"Shell","nbrBytes":11958},{"name":"JavaScript","nbrBytes":5116},{"name":"Python","nbrBytes":323},{"name":"Makefile","nbrBytes":122},{"name":"Ruby","nbrBytes":73}]},{"name":"qubes-gui-agent-windows","html_url":"https://github.com/QubesOS/qubes-gui-agent-windows","id":31260853,"languages_url":"https://api.github.com/repos/QubesOS/qubes-gui-agent-windows/languages","created_at":"2015-02-24T13:18:48Z","languages":[{"name":"C","nbrBytes":234817},{"name":"C++","nbrBytes":19513},{"name":"Objective-C","nbrBytes":13526},{"name":"Shell","nbrBytes":5100},{"name":"C#","nbrBytes":1892},{"name":"PowerShell","nbrBytes":794},{"name":"Makefile","nbrBytes":539},{"name":"Ruby","nbrBytes":273}]},{"name":"qubes-linux-dom0-updates","html_url":"https://github.com/QubesOS/qubes-linux-dom0-updates","id":33508063,"languages_url":"https://api.github.com/repos/QubesOS/qubes-linux-dom0-updates/languages","created_at":"2015-04-06T21:59:20Z","languages":[{"name":"Ruby","nbrBytes":1473}]},{"name":"qubes-builder-fedora","html_url":"https://github.com/QubesOS/qubes-builder-fedora","id":32959619,"languages_url":"https://api.github.com/repos/QubesOS/qubes-builder-fedora/languages","created_at":"2015-03-27T00:36:30Z","languages":[{"name":"Shell","nbrBytes":25936},{"name":"Ruby","nbrBytes":258}]},{"name":"qubes-builder-debian","html_url":"https://github.com/QubesOS/qubes-builder-debian","id":33460786,"languages_url":"https://api.github.com/repos/QubesOS/qubes-builder-debian/languages","created_at":"2015-04-06T00:59:12Z","languages":[{"name":"Shell","nbrBytes":72274},{"name":"Perl","nbrBytes":53770},{"name":"Python","nbrBytes":15492},{"name":"Makefile","nbrBytes":1623}]},{"name":"qubes-posts","html_url":"https://github.com/QubesOS/qubes-posts","id":33867443,"languages_url":"https://api.github.com/repos/QubesOS/qubes-posts/languages","created_at":"2015-04-13T12:33:12Z","languages":[]},{"name":"qubes-windows-utils","html_url":"https://github.com/QubesOS/qubes-windows-utils","id":31260877,"languages_url":"https://api.github.com/repos/QubesOS/qubes-windows-utils/languages","created_at":"2015-02-24T13:19:14Z","languages":[{"name":"C","nbrBytes":148368},{"name":"Objective-C","nbrBytes":12933},{"name":"PowerShell","nbrBytes":1246},{"name":"Ruby","nbrBytes":254},{"name":"Batchfile","nbrBytes":44}]},{"name":"qubes-issues","html_url":"https://github.com/QubesOS/qubes-issues","id":31769954,"languages_url":"https://api.github.com/repos/QubesOS/qubes-issues/languages","created_at":"2015-03-06T13:15:38Z","languages":[]},{"name":"qubes-builder-archlinux","html_url":"https://github.com/QubesOS/qubes-builder-archlinux","id":31986678,"languages_url":"https://api.github.com/repos/QubesOS/qubes-builder-archlinux/languages","created_at":"2015-03-10T23:07:28Z","languages":[{"name":"Shell","nbrBytes":21164},{"name":"Makefile","nbrBytes":271}]},{"name":"qubes-installer-qubes-os-windows-tools","html_url":"https://github.com/QubesOS/qubes-installer-qubes-os-windows-tools","id":31260927,"languages_url":"https://api.github.com/repos/QubesOS/qubes-installer-qubes-os-windows-tools/languages","created_at":"2015-02-24T13:20:46Z","languages":[{"name":"C","nbrBytes":3079},{"name":"Ruby","nbrBytes":1511},{"name":"Batchfile","nbrBytes":820},{"name":"PowerShell","nbrBytes":423}]},{"name":"qubes-doc","html_url":"https://github.com/QubesOS/qubes-doc","id":33867469,"languages_url":"https://api.github.com/repos/QubesOS/qubes-doc/languages","created_at":"2015-04-13T12:33:42Z","languages":[{"name":"HTML","nbrBytes":11372},{"name":"Makefile","nbrBytes":6802},{"name":"Python","nbrBytes":6329}]},{"name":"qubes-attachment","html_url":"https://github.com/QubesOS/qubes-attachment","id":33867607,"languages_url":"https://api.github.com/repos/QubesOS/qubes-attachment/languages","created_at":"2015-04-13T12:36:58Z","languages":[]},{"name":"qubes-hcl","html_url":"https://github.com/QubesOS/qubes-hcl","id":33867564,"languages_url":"https://api.github.com/repos/QubesOS/qubes-hcl/languages","created_at":"2015-04-13T12:35:51Z","languages":[]},{"name":"qubes-linux-deb","html_url":"https://github.com/QubesOS/qubes-linux-deb","id":34675143,"languages_url":"https://api.github.com/repos/QubesOS/qubes-linux-deb/languages","created_at":"2015-04-27T15:36:21Z","languages":[{"name":"Shell","nbrBytes":5303}]},{"name":"qubes-template-configs","html_url":"https://github.com/QubesOS/qubes-template-configs","id":35786611,"languages_url":"https://api.github.com/repos/QubesOS/qubes-template-configs/languages","created_at":"2015-05-17T23:09:03Z","languages":[{"name":"Makefile","nbrBytes":54199}]},{"name":"qubes-app-linux-img-converter","html_url":"https://github.com/QubesOS/qubes-app-linux-img-converter","id":35823264,"languages_url":"https://api.github.com/repos/QubesOS/qubes-app-linux-img-converter/languages","created_at":"2015-05-18T14:39:39Z","languages":[{"name":"Python","nbrBytes":7307},{"name":"Makefile","nbrBytes":4526},{"name":"Shell","nbrBytes":858},{"name":"Groff","nbrBytes":634}]},{"name":"qubes-vmm-xen-win-pvdrivers-xeniface","html_url":"https://github.com/QubesOS/qubes-vmm-xen-win-pvdrivers-xeniface","id":36321566,"languages_url":"https://api.github.com/repos/QubesOS/qubes-vmm-xen-win-pvdrivers-xeniface/languages","created_at":"2015-05-26T20:22:47Z","languages":[{"name":"C","nbrBytes":440079},{"name":"C++","nbrBytes":52232},{"name":"Objective-C","nbrBytes":48058},{"name":"Python","nbrBytes":14757},{"name":"Batchfile","nbrBytes":1260}]},{"name":"qubes-app-linux-input-proxy","html_url":"https://github.com/QubesOS/qubes-app-linux-input-proxy","id":43584857,"languages_url":"https://api.github.com/repos/QubesOS/qubes-app-linux-input-proxy/languages","created_at":"2015-10-03T02:13:29Z","languages":[{"name":"C","nbrBytes":20638},{"name":"Python","nbrBytes":14957},{"name":"Makefile","nbrBytes":1902},{"name":"Ruby","nbrBytes":710}]},{"name":"qubes-roadmap","html_url":"https://github.com/QubesOS/qubes-roadmap","id":40120882,"languages_url":"https://api.github.com/repos/QubesOS/qubes-roadmap/languages","created_at":"2015-08-03T11:20:42Z","languages":[]},{"name":"qubes-builder-windows","html_url":"https://github.com/QubesOS/qubes-builder-windows","id":36330294,"languages_url":"https://api.github.com/repos/QubesOS/qubes-builder-windows/languages","created_at":"2015-05-26T23:33:52Z","languages":[{"name":"PowerShell","nbrBytes":31505},{"name":"C#","nbrBytes":6589},{"name":"Batchfile","nbrBytes":3015},{"name":"Shell","nbrBytes":812},{"name":"Ruby","nbrBytes":335}]},{"name":"qubes-vmm-xen-win-pvdrivers-xenbus","html_url":"https://github.com/QubesOS/qubes-vmm-xen-win-pvdrivers-xenbus","id":36321539,"languages_url":"https://api.github.com/repos/QubesOS/qubes-vmm-xen-win-pvdrivers-xenbus/languages","created_at":"2015-05-26T20:22:05Z","languages":[{"name":"C","nbrBytes":1308143},{"name":"Objective-C","nbrBytes":66582},{"name":"Python","nbrBytes":16434},{"name":"C++","nbrBytes":14757},{"name":"Assembly","nbrBytes":3365},{"name":"Batchfile","nbrBytes":197}]},{"name":"qubes-linux-pvgrub2","html_url":"https://github.com/QubesOS/qubes-linux-pvgrub2","id":45761734,"languages_url":"https://api.github.com/repos/QubesOS/qubes-linux-pvgrub2/languages","created_at":"2015-11-08T01:08:19Z","languages":[{"name":"Makefile","nbrBytes":1882},{"name":"Ruby","nbrBytes":69}]},{"name":"qubes-mgmt-salt-base","html_url":"https://github.com/QubesOS/qubes-mgmt-salt-base","id":46565489,"languages_url":"https://api.github.com/repos/QubesOS/qubes-mgmt-salt-base/languages","created_at":"2015-11-20T14:07:57Z","languages":[{"name":"Python","nbrBytes":39773},{"name":"Makefile","nbrBytes":1647}]},{"name":"qubes-builder-github","html_url":"https://github.com/QubesOS/qubes-builder-github","id":44911360,"languages_url":"https://api.github.com/repos/QubesOS/qubes-builder-github/languages","created_at":"2015-10-25T13:32:57Z","languages":[{"name":"Python","nbrBytes":20390},{"name":"Shell","nbrBytes":8716},{"name":"Makefile","nbrBytes":486}]},{"name":"qubes-mgmt-salt-base-config","html_url":"https://github.com/QubesOS/qubes-mgmt-salt-base-config","id":46565494,"languages_url":"https://api.github.com/repos/QubesOS/qubes-mgmt-salt-base-config/languages","created_at":"2015-11-20T14:08:00Z","languages":[{"name":"Makefile","nbrBytes":1556},{"name":"SaltStack","nbrBytes":437},{"name":"HTML","nbrBytes":221}]},{"name":"qubes-mgmt-salt-dom0-virtual-machines","html_url":"https://github.com/QubesOS/qubes-mgmt-salt-dom0-virtual-machines","id":46565498,"languages_url":"https://api.github.com/repos/QubesOS/qubes-mgmt-salt-dom0-virtual-machines/languages","created_at":"2015-11-20T14:08:03Z","languages":[{"name":"Makefile","nbrBytes":1979},{"name":"Shell","nbrBytes":1445}]},{"name":"qubes-mgmt-salt-dom0-qvm","html_url":"https://github.com/QubesOS/qubes-mgmt-salt-dom0-qvm","id":46565496,"languages_url":"https://api.github.com/repos/QubesOS/qubes-mgmt-salt-dom0-qvm/languages","created_at":"2015-11-20T14:08:02Z","languages":[{"name":"Python","nbrBytes":70381},{"name":"Shell","nbrBytes":22115},{"name":"Makefile","nbrBytes":1864}]},{"name":"qubes-mgmt-salt-dom0-update","html_url":"https://github.com/QubesOS/qubes-mgmt-salt-dom0-update","id":46565499,"languages_url":"https://api.github.com/repos/QubesOS/qubes-mgmt-salt-dom0-update/languages","created_at":"2015-11-20T14:08:05Z","languages":[{"name":"Python","nbrBytes":103222},{"name":"Makefile","nbrBytes":1867},{"name":"Shell","nbrBytes":1646}]},{"name":"qubes-mgmt-salt","html_url":"https://github.com/QubesOS/qubes-mgmt-salt","id":46695438,"languages_url":"https://api.github.com/repos/QubesOS/qubes-mgmt-salt/languages","created_at":"2015-11-23T03:54:33Z","languages":[{"name":"Shell","nbrBytes":27057},{"name":"Python","nbrBytes":20436},{"name":"Makefile","nbrBytes":9404},{"name":"SaltStack","nbrBytes":111}]},{"name":"qubes-mgmt-salt-base-topd","html_url":"https://github.com/QubesOS/qubes-mgmt-salt-base-topd","id":46565491,"languages_url":"https://api.github.com/repos/QubesOS/qubes-mgmt-salt-base-topd/languages","created_at":"2015-11-20T14:07:59Z","languages":[{"name":"Python","nbrBytes":73654},{"name":"Makefile","nbrBytes":1751}]},{"name":"qubes-mgmt-salt-base-overrides","html_url":"https://github.com/QubesOS/qubes-mgmt-salt-base-overrides","id":46696208,"languages_url":"https://api.github.com/repos/QubesOS/qubes-mgmt-salt-base-overrides/languages","created_at":"2015-11-23T04:17:55Z","languages":[{"name":"Python","nbrBytes":17529},{"name":"Makefile","nbrBytes":1556}]},{"name":"build-issues","html_url":"https://github.com/QubesOS/build-issues","id":76301571,"languages_url":"https://api.github.com/repos/QubesOS/build-issues/languages","created_at":"2016-12-12T22:36:43Z","languages":[]},{"name":"qubes-desktop-linux-i3","html_url":"https://github.com/QubesOS/qubes-desktop-linux-i3","id":59559858,"languages_url":"https://api.github.com/repos/QubesOS/qubes-desktop-linux-i3/languages","created_at":"2016-05-24T09:33:48Z","languages":[{"name":"Shell","nbrBytes":4593},{"name":"Makefile","nbrBytes":436},{"name":"Ruby","nbrBytes":103}]},{"name":"qubes-app-linux-usb-proxy","html_url":"https://github.com/QubesOS/qubes-app-linux-usb-proxy","id":54812934,"languages_url":"https://api.github.com/repos/QubesOS/qubes-app-linux-usb-proxy/languages","created_at":"2016-03-27T04:40:57Z","languages":[{"name":"Python","nbrBytes":28876},{"name":"Shell","nbrBytes":8326},{"name":"Makefile","nbrBytes":457},{"name":"Ruby","nbrBytes":219}]},{"name":"training-materials","html_url":"https://github.com/QubesOS/training-materials","id":54214042,"languages_url":"https://api.github.com/repos/QubesOS/training-materials/languages","created_at":"2016-03-18T16:00:26Z","languages":[]},{"name":"qubes-core-admin-client","html_url":"https://github.com/QubesOS/qubes-core-admin-client","id":82980637,"languages_url":"https://api.github.com/repos/QubesOS/qubes-core-admin-client/languages","created_at":"2017-02-23T23:15:15Z","languages":[{"name":"Python","nbrBytes":812770},{"name":"Shell","nbrBytes":438},{"name":"Makefile","nbrBytes":300},{"name":"Ruby","nbrBytes":84}]},{"name":"qubes-desktop-linux-awesome","html_url":"https://github.com/QubesOS/qubes-desktop-linux-awesome","id":61590588,"languages_url":"https://api.github.com/repos/QubesOS/qubes-desktop-linux-awesome/languages","created_at":"2016-06-21T00:49:15Z","languages":[{"name":"Makefile","nbrBytes":1879},{"name":"Ruby","nbrBytes":64}]},{"name":"build-logs","html_url":"https://github.com/QubesOS/build-logs","id":75689786,"languages_url":"https://api.github.com/repos/QubesOS/build-logs/languages","created_at":"2016-12-06T03:12:46Z","languages":[{"name":"Roff","nbrBytes":93025158},{"name":"Shell","nbrBytes":817}]},{"name":"qubes-app-yubikey","html_url":"https://github.com/QubesOS/qubes-app-yubikey","id":62099321,"languages_url":"https://api.github.com/repos/QubesOS/qubes-app-yubikey/languages","created_at":"2016-06-28T01:13:45Z","languages":[{"name":"Shell","nbrBytes":1385},{"name":"Ruby","nbrBytes":107}]},{"name":"qubes-linux-scrypt","html_url":"https://github.com/QubesOS/qubes-linux-scrypt","id":70113304,"languages_url":"https://api.github.com/repos/QubesOS/qubes-linux-scrypt/languages","created_at":"2016-10-06T01:27:14Z","languages":[{"name":"Ruby","nbrBytes":87},{"name":"Makefile","nbrBytes":49}]},{"name":"qubes-infrastructure","html_url":"https://github.com/QubesOS/qubes-infrastructure","id":79975193,"languages_url":"https://api.github.com/repos/QubesOS/qubes-infrastructure/languages","created_at":"2017-01-25T02:13:32Z","languages":[{"name":"SaltStack","nbrBytes":11719},{"name":"Makefile","nbrBytes":1862},{"name":"Python","nbrBytes":675}]},{"name":"updates-status","html_url":"https://github.com/QubesOS/updates-status","id":84013162,"languages_url":"https://api.github.com/repos/QubesOS/updates-status/languages","created_at":"2017-03-06T00:26:53Z","languages":[]},{"name":"qubes-vmm-xen-stubdom-linux","html_url":"https://github.com/QubesOS/qubes-vmm-xen-stubdom-linux","id":90686980,"languages_url":"https://api.github.com/repos/QubesOS/qubes-vmm-xen-stubdom-linux/languages","created_at":"2017-05-09T01:06:48Z","languages":[{"name":"Shell","nbrBytes":8148},{"name":"Makefile","nbrBytes":1874},{"name":"Ruby","nbrBytes":87}]},{"name":"qubes-desktop-linux-common","html_url":"https://github.com/QubesOS/qubes-desktop-linux-common","id":88909144,"languages_url":"https://api.github.com/repos/QubesOS/qubes-desktop-linux-common/languages","created_at":"2017-04-20T20:47:17Z","languages":[{"name":"Python","nbrBytes":62923},{"name":"Makefile","nbrBytes":1499},{"name":"Shell","nbrBytes":248},{"name":"Ruby","nbrBytes":81}]},{"name":"qubes-meta-packages","html_url":"https://github.com/QubesOS/qubes-meta-packages","id":92831898,"languages_url":"https://api.github.com/repos/QubesOS/qubes-meta-packages/languages","created_at":"2017-05-30T12:45:08Z","languages":[{"name":"Makefile","nbrBytes":1001}]},{"name":"qubes-dbus","html_url":"https://github.com/QubesOS/qubes-dbus","id":96360913,"languages_url":"https://api.github.com/repos/QubesOS/qubes-dbus/languages","created_at":"2017-07-05T21:01:54Z","languages":[{"name":"Python","nbrBytes":55709},{"name":"Ruby","nbrBytes":90}]},{"name":"qubes-python-xcffib","html_url":"https://github.com/QubesOS/qubes-python-xcffib","id":105305261,"languages_url":"https://api.github.com/repos/QubesOS/qubes-python-xcffib/languages","created_at":"2017-09-29T18:34:51Z","languages":[{"name":"Ruby","nbrBytes":37}]},{"name":"qubes-linux-gbulb","html_url":"https://github.com/QubesOS/qubes-linux-gbulb","id":98695643,"languages_url":"https://api.github.com/repos/QubesOS/qubes-linux-gbulb/languages","created_at":"2017-07-28T23:35:09Z","languages":[{"name":"Ruby","nbrBytes":37}]},{"name":"qubes-builder-centos","html_url":"https://github.com/QubesOS/qubes-builder-centos","id":105260352,"languages_url":"https://api.github.com/repos/QubesOS/qubes-builder-centos/languages","created_at":"2017-09-29T10:27:36Z","languages":[{"name":"Shell","nbrBytes":20285},{"name":"Ruby","nbrBytes":262}]},{"name":"qubes-desktop-linux-manager","html_url":"https://github.com/QubesOS/qubes-desktop-linux-manager","id":96360684,"languages_url":"https://api.github.com/repos/QubesOS/qubes-desktop-linux-manager/languages","created_at":"2017-07-05T20:58:50Z","languages":[{"name":"Python","nbrBytes":63572},{"name":"Ruby","nbrBytes":107}]}]}